canvas_markup
