Metadata-Version: 2.1
Name: canvas-markup
Version: 1.0.1
Summary: Canvas-markup generates images
Home-page: https://github.com/Xpos587/Canvas-markup-py
Download-URL: https://github.com/Xpos587/Canvas-markup-py/tree/master/releases/v1.0.1.zip
Author: Xpos587
Author-email: x30827pos@gmail.com
License: MIT License, Copyright (c) 2022 Xpos587, see LICENSE file.
Requires: os
Requires: pyppeteer
Requires: jinja2
Requires: asyncio
License-File: LICENSE
